mqp/__init__.py
mqp/qiskit_provider/__init__.py
mqp/qiskit_provider/backend.py
mqp/qiskit_provider/job.py
mqp/qiskit_provider/mqp_resources.py
mqp/qiskit_provider/provider.py
mqp_qiskit_provider-0.1.7.dist-info/METADATA
mqp_qiskit_provider-0.1.7.dist-info/WHEEL
mqp_qiskit_provider-0.1.7.dist-info/entry_points.txt
mqp_qiskit_provider-0.1.7.dist-info/licenses/LICENSE
mqp_qiskit_provider-0.1.7.dist-info/RECORD
