Metadata-Version: 2.1
Name: mqp-qiskit-provider
Version: 0.1.7
Summary: A provider for Qiskit interface to MQP.
Author-Email: mqss <mqss@munich-quantum-valley.de>
License: Apache-2.0
Requires-Python: <3.12,>=3.8
Requires-Dist: qiskit<1.3,>=0.45
Requires-Dist: requests>=2.32.3
Requires-Dist: python-decouple>=3.8
Requires-Dist: mqp-client>=0.1.5
Requires-Dist: qiskit-qasm3-import>=0.5.1
Provides-Extra: docs
Requires-Dist: mkdocs>=1.6.1; extra == "docs"
Requires-Dist: mkdocs-material>=9.6.2; extra == "docs"
Requires-Dist: mkdocstrings[python]>=0.26.1; extra == "docs"
Requires-Dist: mkdocs-autorefs>=1.2.0; extra == "docs"
